Workbook

Sheet README
B1: Samvardhani Compensation Calculator
B3: Companion spreadsheet to compensation-plan-reference.md in this repo. Use it to manually verify the app's calculated payouts against expected values, and as a source of test fixtures for backend unit tests.
B5: Sheets:
B6: Rates & Slabs — every percentage, deduction, and tier threshold, editable. Every other sheet formula-references this one — change a rate here and every example/calculation recalculates.
B7: Round 1 Example — the two-sponsee worked example from the guide, reproduced with live formulas. Expected total: ₹2,05,000 + Smart Watch.
B8: Round 2 Example — the four-grandchild worked example, reproduced with live formulas. Expected total: ₹4,48,490 + Smart Watch + Manali + Goa (using the volume-slab Royalty reading — see the discrepancy note below).
B9: Calculator (Your Numbers) — blank input cells (yellow) for pasting in real test values from the app; computes gross, TDS, admin charge, and net for each income line.
B11: ⚠️ KNOWN DISCREPANCY — read before trusting Royalty Bonus numbers:
B12: The source PDFs describe Royalty Bonus as keyed to a volume slab on THIS CLOSING's new matched business (see the Royalty Bonus table on the Rates & Slabs sheet). The already-implemented backend (CycleService.creditRoyalty(), see compensation-plan-reference.md §5) instead looks up Royalty by the associate's RANK, via RoyaltyBonusRateRepository. These are two different formulas and will disagree for real associates. This spreadsheet implements the volume-slab (PDF) formula only — it CANNOT reproduce the rank-keyed formula without also knowing each associate's rank and the plan's rank→rate table, which isn't in the source PDFs. Get this resolved with whoever owns the compensation plan before treating either number as final for Royalty Bonus test assertions.
B14: Also flagged in compensation-plan-reference.md §8:
B15: - No documented base commission for a personal sale under 2,000 sqft.
B16: - Round 1's ₹15,000 reward is paid on a ₹10L pair even though the reward ladder's first tier is ₹5L — reproduced as-is from the source, not corrected.

Sheet Rates & Slabs
B1: Samvardhani Compensation Plan — Rates & Slabs
B2: Edit the values in this sheet — every other sheet recalculates from these cells.
B4: Flat rates
B5: Direct Income % | C5: 0.06
B6: Matching Income % | C6: 0.07
B7: Sponsor's Matching Bonus % | C7: 0.11
B8: Self-Performance Bonus — 2,000 sqft+ closing (extra %) | C8: 0.01
B9: Self-Performance Bonus — 3,000 sqft+ closing (extra %) | C9: 0.02
B10: TDS % | C10: 0.02
B11: Admin Charge — PAN on file % | C11: 0.05
B12: Admin Charge — no PAN on file % | C12: 0.15
B13: ID Activation Fee (₹, one-time) | C13: 1100
B15: Royalty Bonus — new matched business this closing
B16: Matched volume ≥ | C16: Royalty %
B17: 2000000 | C17: 0.01
B18: 4000000 | C18: 0.015
B19: 8000000 | C19: 0.02
B20: 15000000 | C20: 0.025
B21: 30000000 | C21: 0.03
B22: Source note: "Royalty Bonus will Calculate on the Bonus of New Matching Business in a Single Closing." This is volume-slab-keyed, NOT rank-keyed — see README and compensation-plan-reference.md §5 for a discrepancy against the implemented app logic, which is rank-keyed.
B24: Reward Income ladder — cumulative matched business, one-time per tier
B25: Cumulative matched ≥ | C25: Designation | D25: Cash reward | E25: Perk
B26: 500000 | C26: Sales Associate | D26: 15000 | E26: Smart Watch
B27: 1000000 | C27: Sales Executive | D27: 20000 | E27: Manali, 2N/3D
B28: 2000000 | C28: Senior Sales Executive | D28: 45000 | E28: Goa, 3N/4D
B29: 4000000 | C29: Sales Manager | D29: 90000 | E29: Thailand, 4N/5D
B30: 8000000 | C30: Senior Sales Manager | D30: 180000 | E30: Dubai, 5N/6D
B31: 15000000 | C31: Territory Manager | D31: 400000 | E31: or a mini car
B32: 30000000 | C32: Chief Manager | D32: 800000 | E32: or a big car
B33: 60000000 | C33: Assistant General Manager | D33: 1600000 | E33: or a premium car
B34: 120000000 | C34: General Manager | D34: 3200000 | E34: or a luxury car
B35: 250000000 | C35: Vice President | D35: 6400000 | E35: or a 2BHK flat
B36: 500000000 | C36: President | D36: 15000000 | E36: or a bungalow
B37: 1000000000 | C37: Sales Director | D37: 30000000 | E37: + 5% profit share
B39: A tier is awarded once, ever, the first cycle it's crossed — matches the implemented app's RewardTier logic (checked without a cycleId filter).

Sheet Round 1 Example
B1: Round 1 — A and B each close a sale
B2: Matches compensation-plan-reference.md §6, Round 1.
B4: Inputs
B5: A's sale amount | C5: 1000000
B6: B's sale amount | C6: 1000000
B8: Calculated income
B9: Direct Income | C9: =('Round 1 Example'!$C$5*'Rates & Slabs'!$C$5)+('Round 1 Example'!$C$6*'Rates & Slabs'!$C$5) | D9: 6% of A's sale + 6% of B's sale
B10: Matched volume (min of the two) | C10: =MIN('Round 1 Example'!$C$5,'Round 1 Example'!$C$6)
B11: Matching Income | C11: ='Round 1 Example'!$C$10*'Rates & Slabs'!$C$6 | D11: 7% of the matched volume above
B12: Reward Income (per source's own worked example) | C12: 15000 | D12: Source pays the ₹5L-tier reward (₹15,000 + Smart Watch) here even though the matched volume is ₹10L, not ₹5L — reproduced as-is; see reference doc §8, gap #2.
B14: Total
B15: Total after Round 1 | C15: ='Round 1 Example'!$C$9+'Round 1 Example'!$C$11+'Round 1 Example'!$C$12 | D15: + Smart Watch (perk, not cash)
B17: Expected total: ₹2,05,000 + Smart Watch. If your app returns something else for these exact inputs, that's a real mismatch to investigate.

Sheet Round 2 Example
B1: Round 2 — A and B's own teams start selling
B2: Matches compensation-plan-reference.md §6, Round 2.
B4: Inputs
B5: C's sale (under A, left) | C5: 3000000
B6: D's sale (under A, right) | C6: 2000000
B7: E's sale (under B, left) | C7: 2300000
B8: F's sale (under B, right) | C8: 1700000
B10: Leg totals
B11: Your Left Leg total (C + D) | C11: ='Round 2 Example'!$C$5+'Round 2 Example'!$C$6
B12: Your Right Leg total (E + F) | C12: ='Round 2 Example'!$C$7+'Round 2 Example'!$C$8
B14: Your income
B15: Your matched volume | C15: =MIN('Round 2 Example'!$C$11,'Round 2 Example'!$C$12)
B16: Your Matching Income | C16: ='Round 2 Example'!$C$15*'Rates & Slabs'!$C$6
B18: A and B's own Matching Income (intermediate)
B19: A's matched volume (min of C, D) | C19: =MIN('Round 2 Example'!$C$5,'Round 2 Example'!$C$6)
B20: A's Matching Income | C20: =C19*'Rates & Slabs'!$C$6
B21: B's matched volume (min of E, F) | C21: =MIN('Round 2 Example'!$C$7,'Round 2 Example'!$C$8)
B22: B's Matching Income | C22: =C21*'Rates & Slabs'!$C$6
B24: Your Sponsor's Matching Bonus
B25: From A (11% of A's Matching Income) | C25: ='Round 2 Example'!$C$20*'Rates & Slabs'!$C$7
B26: From B (11% of B's Matching Income) | C26: ='Round 2 Example'!$C$22*'Rates & Slabs'!$C$7
B27: Total Sponsor's Matching Bonus | C27: ='Round 2 Example'!$C$25+'Round 2 Example'!$C$26
B29: Royalty Bonus — two competing formulas (see §5 discrepancy)
B30: Royalty Bonus — volume-slab method (per source PDFs) | C30: =IFERROR(VLOOKUP('Round 2 Example'!$C$15,'Rates & Slabs'!$B$17:$C$21,2,TRUE),0)*'Round 2 Example'!$C$15
B31: Royalty Bonus — rank-keyed method (as implemented in the app) | C31: Depends on rankId — not computable from volume alone
B33: Reward Income (cumulative, per source's own worked example)
B34: Level 1 (₹5L tier) | C34: 15000
B35: Level 2 (₹10L tier) | C35: 20000
B36: Level 3 (₹20L tier) | C36: 45000
B37: Total Reward Income | C37: =SUM(C34:C36)
B39: Total (using volume-slab Royalty)
B40: Total after Round 2 | C40: ='Round 2 Example'!$C$16+'Round 2 Example'!$C$27+'Round 2 Example'!$C$30+'Round 2 Example'!$C$37 | D40: + Smart Watch + Manali + Goa (perks, not cash)
B42: Expected total: ₹4,48,490 + Smart Watch + Manali + Goa (using the volume-slab Royalty reading). If the app uses rank-keyed Royalty instead, this total won't match — that's the §5 discrepancy, not a spreadsheet bug.

Sheet Calculator (Your Numbers)
B1: Calculator — plug in real numbers, compare against the app
B2: Same shape as Round 2. Type test values from your app into the yellow cells.
B4: Inputs — type your test values here
B5: C's sale (under A, left) | C5: 0
B6: D's sale (under A, right) | C6: 0
B7: E's sale (under B, left) | C7: 0
B8: F's sale (under B, right) | C8: 0
B10: Associate has PAN on file? (TRUE/FALSE) | C10: TRUE
B12: Leg totals
B13: Left Leg total | C13: ='Calculator (Your Numbers)'!$C$5+'Calculator (Your Numbers)'!$C$6
B14: Right Leg total | C14: ='Calculator (Your Numbers)'!$C$7+'Calculator (Your Numbers)'!$C$8
B16: Calculated income — gross
B17: Your matched volume | C17: =MIN('Calculator (Your Numbers)'!$C$13,'Calculator (Your Numbers)'!$C$14)
B18: Your Matching Income (gross) | C18: ='Calculator (Your Numbers)'!$C$17*'Rates & Slabs'!$C$6
B19: A's matched volume | C19: =MIN('Calculator (Your Numbers)'!$C$5,'Calculator (Your Numbers)'!$C$6)
B20: A's Matching Income | C20: =C19*'Rates & Slabs'!$C$6
B21: B's matched volume | C21: =MIN('Calculator (Your Numbers)'!$C$7,'Calculator (Your Numbers)'!$C$8)
B22: B's Matching Income | C22: =C21*'Rates & Slabs'!$C$6
B23: Sponsor's Matching Bonus (gross) | C23: =('Calculator (Your Numbers)'!$C$20*'Rates & Slabs'!$C$7)+('Calculator (Your Numbers)'!$C$22*'Rates & Slabs'!$C$7)
B24: Royalty Bonus (gross, volume-slab method) | C24: =IFERROR(VLOOKUP('Calculator (Your Numbers)'!$C$17,'Rates & Slabs'!$B$17:$C$21,2,TRUE),0)*'Calculator (Your Numbers)'!$C$17
B25: Reward: designation unlocked at this cumulative volume | C25: =IFERROR(VLOOKUP('Calculator (Your Numbers)'!$C$17,'Rates & Slabs'!$B$26:$E$37,2,TRUE),"—")
B26: Reward: cash (one-time, if newly crossed) | C26: =IFERROR(VLOOKUP('Calculator (Your Numbers)'!$C$17,'Rates & Slabs'!$B$26:$E$37,3,TRUE),0)
B27: Reward: perk | C27: =IFERROR(VLOOKUP('Calculator (Your Numbers)'!$C$17,'Rates & Slabs'!$B$26:$E$37,4,TRUE),"—")
B29: Deductions & net (applied per income line)
B30: Applicable admin charge % | C30: =IF('Calculator (Your Numbers)'!$C$10,'Rates & Slabs'!$C$11,'Rates & Slabs'!$C$12)
B32: Income line | C32: Gross | D32: TDS (2%) | E32: Admin charge | F32: Net
B33: Matching Income | C33: ='Calculator (Your Numbers)'!$C$18 | D33: ='Calculator (Your Numbers)'!$C$33*'Rates & Slabs'!$C$10 | E33: ='Calculator (Your Numbers)'!$C$33*'Calculator (Your Numbers)'!$C$30 | F33: ='Calculator (Your Numbers)'!$C$33-D33-E33
B34: Sponsor's Matching Bonus | C34: ='Calculator (Your Numbers)'!$C$23 | D34: ='Calculator (Your Numbers)'!$C$34*'Rates & Slabs'!$C$10 | E34: ='Calculator (Your Numbers)'!$C$34*'Calculator (Your Numbers)'!$C$30 | F34: ='Calculator (Your Numbers)'!$C$34-D34-E34
B35: Royalty Bonus | C35: ='Calculator (Your Numbers)'!$C$24 | D35: ='Calculator (Your Numbers)'!$C$35*'Rates & Slabs'!$C$10 | E35: ='Calculator (Your Numbers)'!$C$35*'Calculator (Your Numbers)'!$C$30 | F35: ='Calculator (Your Numbers)'!$C$35-D35-E35
B36: Reward Income (cash portion) | C36: ='Calculator (Your Numbers)'!$C$26 | D36: ='Calculator (Your Numbers)'!$C$36*'Rates & Slabs'!$C$10 | E36: ='Calculator (Your Numbers)'!$C$36*'Calculator (Your Numbers)'!$C$30 | F36: ='Calculator (Your Numbers)'!$C$36-D36-E36
B37: Total net payable this cycle | F37: =SUM(F33,F34,F35,F36)
B39: Compare each net figure above against what your app's income statement / ledger shows for the same test inputs. A mismatch on any single line narrows down exactly which formula to check first.
